mailosaur/__init__.py
mailosaur/mailosaur_client.py
mailosaur/version.py
mailosaur/models/__init__.py
mailosaur/models/attachment.py
mailosaur/models/block_list_result.py
mailosaur/models/code.py
mailosaur/models/content.py
mailosaur/models/deliverability_report.py
mailosaur/models/device.py
mailosaur/models/device_create_options.py
mailosaur/models/device_list_result.py
mailosaur/models/dns_records.py
mailosaur/models/email_authentication_result.py
mailosaur/models/email_client.py
mailosaur/models/email_client_list_result.py
mailosaur/models/image.py
mailosaur/models/link.py
mailosaur/models/mailosaur_exception.py
mailosaur/models/message.py
mailosaur/models/message_address.py
mailosaur/models/message_content.py
mailosaur/models/message_create_options.py
mailosaur/models/message_forward_options.py
mailosaur/models/message_header.py
mailosaur/models/message_list_result.py
mailosaur/models/message_reply_options.py
mailosaur/models/message_summary.py
mailosaur/models/metadata.py
mailosaur/models/otp_result.py
mailosaur/models/preview.py
mailosaur/models/preview_list_result.py
mailosaur/models/preview_request_options.py
mailosaur/models/result_enum.py
mailosaur/models/search_criteria.py
mailosaur/models/server.py
mailosaur/models/server_create_options.py
mailosaur/models/server_list_result.py
mailosaur/models/spam_analysis_result.py
mailosaur/models/spam_assassin_result.py
mailosaur/models/spam_assassin_rule.py
mailosaur/models/spam_filter_results.py
mailosaur/models/usage_account_limit.py
mailosaur/models/usage_account_limits.py
mailosaur/models/usage_transaction.py
mailosaur/models/usage_transaction_list_result.py
mailosaur/operations/__init__.py
mailosaur/operations/analysis_operations.py
mailosaur/operations/devices_operations.py
mailosaur/operations/files_operations.py
mailosaur/operations/messages_operations.py
mailosaur/operations/previews_operations.py
mailosaur/operations/servers_operations.py
mailosaur/operations/usage_operations.py
mailosaur-8.0.0.dist-info/licenses/LICENSE
tests/__init__.py
mailosaur-8.0.0.dist-info/METADATA
mailosaur-8.0.0.dist-info/WHEEL
mailosaur-8.0.0.dist-info/top_level.txt
mailosaur-8.0.0.dist-info/RECORD
