Metadata-Version: 2.4
Name: mailosaur
Version: 8.0.0
Summary: The Mailosaur Python library lets you integrate email and SMS testing into your continuous integration process.
Home-page: https://github.com/mailosaur/mailosaur-python
Author: Mailosaur Ltd
Author-email: code@mailosaur.com
License: MIT
Project-URL: Bug Tracker, https://github.com/mailosaur/mailosaur-python/issues
Project-URL: Documentation, https://mailosaur.com/docs/email-testing/python/
Project-URL: Source Code, https://github.com/mailosaur/mailosaur-python
Keywords: email sms testing automation selenium robot framework
Classifier: Development Status :: 5 - Production/Stable
Classifier: Intended Audience :: Developers
Classifier: License :: OSI Approved :: MIT License
Classifier: Operating System :: OS Independent
Classifier: Programming Language :: Python
Classifier: Programming Language :: Python :: 2
Classifier: Programming Language :: Python :: 2.7
Classifier: Programming Language :: Python :: 3
Classifier: Programming Language :: Python :: 3.4
Classifier: Programming Language :: Python :: 3.5
Classifier: Programming Language :: Python :: 3.6
Classifier: Programming Language :: Python :: 3.7
Classifier: Programming Language :: Python :: Implementation :: PyPy
Classifier: Topic :: Software Development :: Quality Assurance
Classifier: Topic :: Software Development :: Testing
Classifier: Topic :: Software Development :: Libraries :: Python Modules
Requires: requests
Requires-Python: >=2.7, !=3.0.*, !=3.1.*, !=3.2.*, !=3.3.*
License-File: LICENSE
Requires-Dist: python-dateutil
Requires-Dist: tzlocal
Requires-Dist: requests
Requires-Dist: requests[security]
Dynamic: author
Dynamic: author-email
Dynamic: classifier
Dynamic: description
Dynamic: description-content-type
Dynamic: home-page
Dynamic: keywords
Dynamic: license
Dynamic: license-file
Dynamic: project-url
Dynamic: requires
Dynamic: requires-dist
Dynamic: requires-python
Dynamic: summary
